<entries>
  <entry key="env">
    <int>INT</int>
    <uat>UAT</uat>
    <prod>PROD</prod>
  </entry>
  <entry key="ldap-healthcheck.hostname">
    <int>ldap-healthcheck-liberty.kube.intisbank</int>
    <uat>ldap-healthcheck-liberty.kube.uatisbank</uat>
    <prod>ldap-healthcheck-liberty.kube.isbank</prod>
  </entry>
  <entry key="kafka_host1">
    <int>'klmetkfkt1.uatisbank:9092'</int>
    <uat>'klmetkfkt1.uatisbank:9092'</uat>
    <prod>'klmetkfk01.isbank:9092'</prod>
  </entry>
    <entry key="kafka_host2">
    <int>'klmetkfkt2.uatisbank:9092'</int>
    <uat>'klmetkfkt2.uatisbank:9092'</uat>
    <prod>'klmetkfk02.isbank:9092'</prod>
  </entry>
    <entry key="kafka_host3">
    <int>'klmetkfkt3.uatisbank:9092'</int>
    <uat>'klmetkfkt3.uatisbank:9092'</uat>
    <prod>'klmetkfk03.isbank:9092'</prod>
  </entry>
</entries>